s3_parallel_put/__init__.py
s3_parallel_put/s3_parallel_put.py
s3_parallel_put-0.8.dist-info/LICENSE
s3_parallel_put-0.8.dist-info/METADATA
s3_parallel_put-0.8.dist-info/WHEEL
s3_parallel_put-0.8.dist-info/entry_points.txt
s3_parallel_put-0.8.dist-info/top_level.txt
s3_parallel_put-0.8.dist-info/RECORD
