Metadata-Version: 2.1
Name: s3-parallel-put
Version: 0.8
Summary: s3-parallel-put Parallel uploads to Amazon AWS S3
Home-page: https://github.com/mishudark/s3-parallel-put
Author: mishudark
License: MIT
Keywords: s3 parallel
Platform: UNKNOWN
Classifier: License :: OSI Approved :: MIT License
Classifier: Programming Language :: Python :: 2.7
Requires-Dist: boto (>=2.49.0)
Requires-Dist: python-magic (>=0.4.14)
